rgg/__about__.py
rgg/__init__.py
rgg/__main__.py
rgg/data/grid-bg.png
rgg/data/recommendations-bg.png
rgg-0.0.11.dist-info/METADATA
rgg-0.0.11.dist-info/WHEEL
rgg-0.0.11.dist-info/entry_points.txt
rgg-0.0.11.dist-info/licenses/LICENSE
rgg-0.0.11.dist-info/RECORD
