Metadata-Version: 2.1
Name: rgg
Version: 0.0.11
Summary: Risk plot generator
Project-URL: Bug Reports, https://gitlab.com/0bs1d1an/rgg/issues
Project-URL: Homepage, https://gitlab.com/0bs1d1an/rgg
Project-URL: Source, https://gitlab.com/0bs1d1an/rgg/
Author-email: "Guido Kroon (@0bs1d1an)" <gkroon@maelstrom.ninja>
License-Expression: GPL-3.0-only
License-File: LICENSE
Classifier: Development Status :: 4 - Beta
Classifier: Intended Audience :: Information Technology
Classifier: Intended Audience :: System Administrators
Classifier: License :: OSI Approved :: GNU General Public License v3 (GPLv3)
Classifier: Programming Language :: Python
Classifier: Programming Language :: Python :: 3.6
Classifier: Programming Language :: Python :: 3.7
Classifier: Programming Language :: Python :: 3.8
Classifier: Programming Language :: Python :: 3.9
Classifier: Programming Language :: Python :: 3.10
Classifier: Programming Language :: Python :: 3.11
Classifier: Programming Language :: Python :: Implementation :: CPython
Classifier: Programming Language :: Python :: Implementation :: PyPy
Classifier: Topic :: Security
Requires-Python: >=3.6
Requires-Dist: matplotlib
Requires-Dist: pyyaml
